DLMUSE/__init__.py
DLMUSE/__main__.py
DLMUSE/utils.py
DLMUSE-1.0.3.dist-info/LICENSE
DLMUSE-1.0.3.dist-info/METADATA
DLMUSE-1.0.3.dist-info/WHEEL
DLMUSE-1.0.3.dist-info/entry_points.txt
DLMUSE-1.0.3.dist-info/top_level.txt
DLMUSE-1.0.3.dist-info/RECORD
