Metadata-Version: 2.1
Name: DLMUSE
Version: 1.0.3
Summary: DLMUSE - Deep Learning MUlti-atlas region Segmentation utilizing Ensembles of registration algorithms and parameters
Home-page: https://github.com/CBICA/DLMUSE/
Download-URL: https://github.com/CBICA/DLMUSE/
Author: Guray Erus, Vishnu Bashyam, George Aidinis, Kyunglok Baik, Alexander Getka, Wu Di
Author-email: software@cbica.upenn.edu
Maintainer: George Aidinis, Spiros Maggioros, Kyunglok Baik, Alexander Getka
Maintainer-email: aidinisg@pennmedicine.upenn.edu, Spiros.Maggioros@pennmedicine.upenn.edu, kyunglok.baik@pennmedicine.upenn.edu, alexander.getka@pennmedicine.upenn.edu
License: By installing/using DLMUSE, the user agrees to the following license: See https://www.med.upenn.edu/cbica/software-agreement-non-commercial.html
Keywords: deep learning,image segmentation,semantic segmentation,medical image analysis,medical image segmentation,nnU-Net,nnunet
Classifier: Intended Audience :: Developers
Classifier: Intended Audience :: Science/Research
Classifier: Intended Audience :: Healthcare Industry
Classifier: Programming Language :: Python :: 3
Classifier: Topic :: Scientific/Engineering :: Artificial Intelligence
Classifier: Topic :: Scientific/Engineering :: Image Processing
Classifier: Topic :: Scientific/Engineering :: Medical Science Apps.
Requires-Python: >=3.8
License-File: LICENSE
Requires-Dist: torch>=2.2.1
Requires-Dist: nnunetv2==2.5.1
Requires-Dist: argparse
Requires-Dist: huggingface-hub
Requires-Dist: pathlib
